nagraph/__init__.py
nagraph/graph.py
nagraph-0.1.1.dist-info/licenses/LICENSE
nagraph-0.1.1.dist-info/METADATA
nagraph-0.1.1.dist-info/WHEEL
nagraph-0.1.1.dist-info/top_level.txt
nagraph-0.1.1.dist-info/RECORD
