Metadata-Version: 2.4
Name: nagraph
Version: 0.1.1
Summary: A Python library for graph data structures and algorithms
Author-email: Cerisara Nathan <cerisara.nathan@protonmail.com>
License: MIT License
Project-URL: Homepage, https://github.com/nath54/nagraph
Project-URL: Documentation, https://nath54.github.io/nagraph
Project-URL: Repository, https://github.com/nath54/nagraph
Project-URL: Bug Tracker, https://github.com/nath54/nagraph/issues
Classifier: Programming Language :: Python :: 3
Classifier: License :: OSI Approved :: MIT License
Classifier: Operating System :: OS Independent
Requires-Python: >=3.8
License-File: LICENSE
Requires-Dist: numpy>=1.21.0
Dynamic: license-file
